boardgamegeek.py
pybgg-1.0.0.dist-info/METADATA
pybgg-1.0.0.dist-info/RECORD
pybgg-1.0.0.dist-info/WHEEL
pybgg-1.0.0.dist-info/top_level.txt
